{
 "id": "vae_OMIM:201910_0",
 "subject": {
  "id": "vae_OMIM:201910_0"
 },
 "phenotypicFeatures": [
  {
   "type": {
    "id": "HP:0000870",
    "label": "Increased circulating prolactin concentration"
   }
  },
  {
   "type": {
    "id": "HP:0000953",
    "label": "Hyperpigmentation of the skin"
   }
  },
  {
   "type": {
    "id": "HP:0003154",
    "label": "Increased circulating ACTH level"
   }
  },
  {
   "type": {
    "id": "HP:0008163",
    "label": "Decreased circulating cortisol level"
   }
  },
  {
   "type": {
    "id": "HP:0008665",
    "label": "Clitoral hypertrophy"
   }
  }
 ],
 "diseases": [
  {
   "term": {
    "id": "OMIM:201910",
    "label": "Adrenal hyperplasia, congenital, due to 21-hydroxylase deficiency"
   }
  }
 ],
 "interpretations": [
  {
   "id": "vae_OMIM:201910_0",
   "progressStatus": "SOLVED",
   "diagnosis": {
    "disease": {
     "id": "OMIM:201910",
     "label": "Adrenal hyperplasia, congenital, due to 21-hydroxylase deficiency"
    },
    "genomicInterpretations": [
     {
      "interpretationStatus": "CAUSATIVE",
      "variantInterpretation": {
       "variationDescriptor": {
        "geneContext": {
         "symbol": "CYP21A2"
        }
       }
      }
     }
    ]
   }
  }
 ],
 "metaData": {
  "createdBy": "synthvae",
  "resources": [
   {
    "id": "hp",
    "name": "human phenotype ontology",
    "url": "http://purl.obolibrary.org/obo/hp.owl",
    "namespacePrefix": "HP",
    "iriPrefix": "http://purl.obolibrary.org/obo/HP_"
   }
  ],
  "phenopacketSchemaVersion": "2.0"
 },
 "_synthvae": {
  "synthetic": true,
  "generator": "vae",
  "seed": 0,
  "epochs": 300,
  "min_cases": 20
 }
}